<?xml version="1.0" encoding="US-ASCII" standalone="yes"?><?mso-application progid="Excel.Sheet"?><Workbook xmlns="urn:schemas-microsoft-com:office:spreadsheet" xmlns:o="urn:schemas-microsoft-com:office:office" xmlns:x="urn:schemas-microsoft-com:office:excel" xmlns:ss="urn:schemas-microsoft-com:office:spreadsheet" xmlns:html="http://www.w3.org/TR/REC-html40"><DocumentProperties xmlns="urn:schemas-microsoft-com:office:office"><Author></Author><LastAuthor></LastAuthor><Created></Created><LastSaved></LastSaved><Company></Company><Version></Version></DocumentProperties><ExcelWorkbook  xmlns="urn:schemas-microsoft-com:office:excel"><ProtectStructure>False</ProtectStructure><ProtectWindows>False</ProtectWindows></ExcelWorkbook><Styles><Style ss:ID="Default" ss:Name="Normal"><Alignment ss:Vertical="Bottom"/><Borders/><Font ss:FontName="Calibri" ss:Size="10"/><Interior/><NumberFormat/><Protection/></Style><Style ss:ID="s1"><Font ss:FontName="Calibri" ss:Bold="1" ss:Size="12"/><NumberFormat/></Style><Style ss:ID="s21"><Alignment ss:Horizontal="Center" ss:Vertical="Bottom"/><NumberFormat/><Font ss:FontName="Calibri" ss:Size="10"/><Borders><Border ss:Position="Top" ss:LineStyle="Continuous" ss:Weight="1"/></Borders></Style><Style ss:ID="s22"><Alignment ss:Horizontal="Center" ss:Vertical="Bottom"/><Font ss:FontName="Calibri" ss:Size="10"/><NumberFormat/></Style><Style ss:ID="s23"><Alignment ss:Horizontal="Center" ss:Vertical="Bottom"/><NumberFormat/><Font ss:FontName="Calibri" ss:Size="10"/><Borders><Border ss:Position="Bottom" ss:LineStyle="Continuous" ss:Weight="1"/></Borders></Style><Style ss:ID="s24"><Font ss:FontName="Calibri" ss:Size="10"/><NumberFormat/></Style><Style ss:ID="s31"><Font ss:FontName="Calibri" ss:Size="10"/><Borders><Border ss:Position="Top" ss:LineStyle="Continuous" ss:Weight="1"/></Borders></Style><Style ss:ID="s32"><Font ss:FontName="Calibri" ss:Size="10"/><Borders/></Style><Style ss:ID="s33"><Font ss:FontName="Calibri" ss:Size="10"/><Borders><Border ss:Position="Bottom" ss:LineStyle="Continuous" ss:Weight="1"/></Borders></Style></Styles><Names></Names><Worksheet ss:Name="Sheet1"><Table ss:ExpandedColumnCount="5" ss:ExpandedRowCount="46" x:FullColumns="1" x:FullRows="1"><Column ss:AutoFitWidth="0" ss:Width="126"/><Column ss:AutoFitWidth="0" ss:Width="58"/><Column ss:AutoFitWidth="0" ss:Width="58"/><Column ss:AutoFitWidth="0" ss:Width="58"/><Column ss:AutoFitWidth="0" ss:Width="58"/><Row></Row><Row><Cell ss:StyleID="s31"><Data ss:Type="String"></Data></Cell><Cell ss:StyleID="s21"><Data ss:Type="String">(1)</Data></Cell><Cell ss:StyleID="s21"><Data ss:Type="String">(2)</Data></Cell><Cell ss:StyleID="s21"><Data ss:Type="String">(3)</Data></Cell><Cell ss:StyleID="s21"><Data ss:Type="String">(4)</Data></Cell></Row><Row><Cell ss:StyleID="s32"><Data ss:Type="String">VARIABLES</Data></Cell><Cell ss:StyleID="s22"><Data ss:Type="String">tone</Data></Cell><Cell ss:StyleID="s22"><Data ss:Type="String">tone</Data></Cell><Cell ss:StyleID="s22"><Data ss:Type="String">TONE</Data></Cell><Cell ss:StyleID="s22"><Data ss:Type="String">TONE</Data></Cell></Row><Row><Cell ss:StyleID="s31"><Data ss:Type="String"></Data></Cell><Cell ss:StyleID="s21"><Data ss:Type="String"></Data></Cell><Cell ss:StyleID="s21"><Data ss:Type="String"></Data></Cell><Cell ss:StyleID="s21"><Data ss:Type="String"></Data></Cell><Cell ss:StyleID="s21"><Data ss:Type="String"></Data></Cell></Row><Row><Cell ss:StyleID="s32"><Data ss:Type="String">tone</Data></Cell><Cell ss:StyleID="s22"><Data ss:Type="String">.</Data></Cell><Cell ss:StyleID="s22"><Data ss:Type="String">.</Data></Cell><Cell ss:StyleID="s22"><Data ss:Type="String"></Data></Cell><Cell ss:StyleID="s22"><Data ss:Type="String"></Data></Cell></Row><Row><Cell ss:StyleID="s32"><Data ss:Type="String"></Data></Cell><Cell ss:StyleID="s22"><Data ss:Type="String">(.)</Data></Cell><Cell ss:StyleID="s22"><Data ss:Type="String">(.)</Data></Cell><Cell ss:StyleID="s22"><Data ss:Type="String"></Data></Cell><Cell ss:StyleID="s22"><Data ss:Type="String"></Data></Cell></Row><Row><Cell ss:StyleID="s32"><Data ss:Type="String">201110o.cquarter</Data></Cell><Cell ss:StyleID="s22"><Data ss:Type="String"></Data></Cell><Cell ss:StyleID="s22"><Data ss:Type="String">-</Data></Cell><Cell ss:StyleID="s22"><Data ss:Type="String"></Data></Cell><Cell ss:StyleID="s22"><Data ss:Type="String">-</Data></Cell></Row><Row><Cell ss:StyleID="s32"><Data ss:Type="String"></Data></Cell><Cell ss:StyleID="s22"><Data ss:Type="String"></Data></Cell><Cell ss:StyleID="s22"><Data ss:Type="String"></Data></Cell><Cell ss:StyleID="s22"><Data ss:Type="String"></Data></Cell><Cell ss:StyleID="s22"><Data ss:Type="String"></Data></Cell></Row><Row><Cell ss:StyleID="s32"><Data ss:Type="String">EARN</Data></Cell><Cell ss:StyleID="s22"><Data ss:Type="String">0.0086***</Data></Cell><Cell ss:StyleID="s22"><Data ss:Type="String">0.0048*</Data></Cell><Cell ss:StyleID="s22"><Data ss:Type="String">8.5639***</Data></Cell><Cell ss:StyleID="s22"><Data ss:Type="String">4.8416*</Data></Cell></Row><Row><Cell ss:StyleID="s32"><Data ss:Type="String"></Data></Cell><Cell ss:StyleID="s22"><Data ss:Type="String">(4.33)</Data></Cell><Cell ss:StyleID="s22"><Data ss:Type="String">(1.67)</Data></Cell><Cell ss:StyleID="s22"><Data ss:Type="String">(4.33)</Data></Cell><Cell ss:StyleID="s22"><Data ss:Type="String">(1.67)</Data></Cell></Row><Row><Cell ss:StyleID="s32"><Data ss:Type="String">RET</Data></Cell><Cell ss:StyleID="s22"><Data ss:Type="String">0.0001</Data></Cell><Cell ss:StyleID="s22"><Data ss:Type="String">0.0007***</Data></Cell><Cell ss:StyleID="s22"><Data ss:Type="String">0.0745</Data></Cell><Cell ss:StyleID="s22"><Data ss:Type="String">0.7452***</Data></Cell></Row><Row><Cell ss:StyleID="s32"><Data ss:Type="String"></Data></Cell><Cell ss:StyleID="s22"><Data ss:Type="String">(0.27)</Data></Cell><Cell ss:StyleID="s22"><Data ss:Type="String">(5.17)</Data></Cell><Cell ss:StyleID="s22"><Data ss:Type="String">(0.27)</Data></Cell><Cell ss:StyleID="s22"><Data ss:Type="String">(5.17)</Data></Cell></Row><Row><Cell ss:StyleID="s32"><Data ss:Type="String">SIZE</Data></Cell><Cell ss:StyleID="s22"><Data ss:Type="String">-0.0008***</Data></Cell><Cell ss:StyleID="s22"><Data ss:Type="String">0.0009***</Data></Cell><Cell ss:StyleID="s22"><Data ss:Type="String">-0.8442***</Data></Cell><Cell ss:StyleID="s22"><Data ss:Type="String">0.8647***</Data></Cell></Row><Row><Cell ss:StyleID="s32"><Data ss:Type="String"></Data></Cell><Cell ss:StyleID="s22"><Data ss:Type="String">(-24.60)</Data></Cell><Cell ss:StyleID="s22"><Data ss:Type="String">(4.73)</Data></Cell><Cell ss:StyleID="s22"><Data ss:Type="String">(-24.60)</Data></Cell><Cell ss:StyleID="s22"><Data ss:Type="String">(4.73)</Data></Cell></Row><Row><Cell ss:StyleID="s32"><Data ss:Type="String">MTB</Data></Cell><Cell ss:StyleID="s22"><Data ss:Type="String">0.0000**</Data></Cell><Cell ss:StyleID="s22"><Data ss:Type="String">0.0000</Data></Cell><Cell ss:StyleID="s22"><Data ss:Type="String">0.0281**</Data></Cell><Cell ss:StyleID="s22"><Data ss:Type="String">0.0032</Data></Cell></Row><Row><Cell ss:StyleID="s32"><Data ss:Type="String"></Data></Cell><Cell ss:StyleID="s22"><Data ss:Type="String">(2.37)</Data></Cell><Cell ss:StyleID="s22"><Data ss:Type="String">(0.19)</Data></Cell><Cell ss:StyleID="s22"><Data ss:Type="String">(2.37)</Data></Cell><Cell ss:StyleID="s22"><Data ss:Type="String">(0.19)</Data></Cell></Row><Row><Cell ss:StyleID="s32"><Data ss:Type="String">STD_RET</Data></Cell><Cell ss:StyleID="s22"><Data ss:Type="String">-0.0081***</Data></Cell><Cell ss:StyleID="s22"><Data ss:Type="String">-0.0022***</Data></Cell><Cell ss:StyleID="s22"><Data ss:Type="String">-8.0781***</Data></Cell><Cell ss:StyleID="s22"><Data ss:Type="String">-2.2308***</Data></Cell></Row><Row><Cell ss:StyleID="s32"><Data ss:Type="String"></Data></Cell><Cell ss:StyleID="s22"><Data ss:Type="String">(-7.01)</Data></Cell><Cell ss:StyleID="s22"><Data ss:Type="String">(-3.73)</Data></Cell><Cell ss:StyleID="s22"><Data ss:Type="String">(-7.01)</Data></Cell><Cell ss:StyleID="s22"><Data ss:Type="String">(-3.73)</Data></Cell></Row><Row><Cell ss:StyleID="s32"><Data ss:Type="String">STD_EARN</Data></Cell><Cell ss:StyleID="s22"><Data ss:Type="String">-0.0098***</Data></Cell><Cell ss:StyleID="s22"><Data ss:Type="String">-0.0012</Data></Cell><Cell ss:StyleID="s22"><Data ss:Type="String">-9.7741***</Data></Cell><Cell ss:StyleID="s22"><Data ss:Type="String">-1.1649</Data></Cell></Row><Row><Cell ss:StyleID="s32"><Data ss:Type="String"></Data></Cell><Cell ss:StyleID="s22"><Data ss:Type="String">(-5.01)</Data></Cell><Cell ss:StyleID="s22"><Data ss:Type="String">(-0.55)</Data></Cell><Cell ss:StyleID="s22"><Data ss:Type="String">(-5.01)</Data></Cell><Cell ss:StyleID="s22"><Data ss:Type="String">(-0.55)</Data></Cell></Row><Row><Cell ss:StyleID="s32"><Data ss:Type="String">AGE</Data></Cell><Cell ss:StyleID="s22"><Data ss:Type="String">0.0003***</Data></Cell><Cell ss:StyleID="s22"><Data ss:Type="String">-0.0007*</Data></Cell><Cell ss:StyleID="s22"><Data ss:Type="String">0.3419***</Data></Cell><Cell ss:StyleID="s22"><Data ss:Type="String">-0.7118*</Data></Cell></Row><Row><Cell ss:StyleID="s32"><Data ss:Type="String"></Data></Cell><Cell ss:StyleID="s22"><Data ss:Type="String">(6.39)</Data></Cell><Cell ss:StyleID="s22"><Data ss:Type="String">(-1.73)</Data></Cell><Cell ss:StyleID="s22"><Data ss:Type="String">(6.39)</Data></Cell><Cell ss:StyleID="s22"><Data ss:Type="String">(-1.73)</Data></Cell></Row><Row><Cell ss:StyleID="s32"><Data ss:Type="String">BUSSEG</Data></Cell><Cell ss:StyleID="s22"><Data ss:Type="String">0.0007***</Data></Cell><Cell ss:StyleID="s22"><Data ss:Type="String">0.0001</Data></Cell><Cell ss:StyleID="s22"><Data ss:Type="String">0.6979***</Data></Cell><Cell ss:StyleID="s22"><Data ss:Type="String">0.1153</Data></Cell></Row><Row><Cell ss:StyleID="s32"><Data ss:Type="String"></Data></Cell><Cell ss:StyleID="s22"><Data ss:Type="String">(8.90)</Data></Cell><Cell ss:StyleID="s22"><Data ss:Type="String">(0.39)</Data></Cell><Cell ss:StyleID="s22"><Data ss:Type="String">(8.90)</Data></Cell><Cell ss:StyleID="s22"><Data ss:Type="String">(0.39)</Data></Cell></Row><Row><Cell ss:StyleID="s32"><Data ss:Type="String">GEOSEG</Data></Cell><Cell ss:StyleID="s22"><Data ss:Type="String">-0.0007***</Data></Cell><Cell ss:StyleID="s22"><Data ss:Type="String">0.0002</Data></Cell><Cell ss:StyleID="s22"><Data ss:Type="String">-0.7457***</Data></Cell><Cell ss:StyleID="s22"><Data ss:Type="String">0.2357</Data></Cell></Row><Row><Cell ss:StyleID="s32"><Data ss:Type="String"></Data></Cell><Cell ss:StyleID="s22"><Data ss:Type="String">(-10.79)</Data></Cell><Cell ss:StyleID="s22"><Data ss:Type="String">(0.97)</Data></Cell><Cell ss:StyleID="s22"><Data ss:Type="String">(-10.79)</Data></Cell><Cell ss:StyleID="s22"><Data ss:Type="String">(0.97)</Data></Cell></Row><Row><Cell ss:StyleID="s32"><Data ss:Type="String">LOSS</Data></Cell><Cell ss:StyleID="s22"><Data ss:Type="String">-0.0032***</Data></Cell><Cell ss:StyleID="s22"><Data ss:Type="String">-0.0010***</Data></Cell><Cell ss:StyleID="s22"><Data ss:Type="String">-3.1883***</Data></Cell><Cell ss:StyleID="s22"><Data ss:Type="String">-1.0098***</Data></Cell></Row><Row><Cell ss:StyleID="s32"><Data ss:Type="String"></Data></Cell><Cell ss:StyleID="s22"><Data ss:Type="String">(-18.96)</Data></Cell><Cell ss:StyleID="s22"><Data ss:Type="String">(-7.83)</Data></Cell><Cell ss:StyleID="s22"><Data ss:Type="String">(-18.96)</Data></Cell><Cell ss:StyleID="s22"><Data ss:Type="String">(-7.83)</Data></Cell></Row><Row><Cell ss:StyleID="s32"><Data ss:Type="String">DEARN</Data></Cell><Cell ss:StyleID="s22"><Data ss:Type="String">-0.0065***</Data></Cell><Cell ss:StyleID="s22"><Data ss:Type="String">-0.0033***</Data></Cell><Cell ss:StyleID="s22"><Data ss:Type="String">-6.4977***</Data></Cell><Cell ss:StyleID="s22"><Data ss:Type="String">-3.3271***</Data></Cell></Row><Row><Cell ss:StyleID="s32"><Data ss:Type="String"></Data></Cell><Cell ss:StyleID="s22"><Data ss:Type="String">(-3.59)</Data></Cell><Cell ss:StyleID="s22"><Data ss:Type="String">(-2.90)</Data></Cell><Cell ss:StyleID="s22"><Data ss:Type="String">(-3.59)</Data></Cell><Cell ss:StyleID="s22"><Data ss:Type="String">(-2.90)</Data></Cell></Row><Row><Cell ss:StyleID="s32"><Data ss:Type="String">AFE</Data></Cell><Cell ss:StyleID="s22"><Data ss:Type="String">0.0035**</Data></Cell><Cell ss:StyleID="s22"><Data ss:Type="String">0.0039***</Data></Cell><Cell ss:StyleID="s22"><Data ss:Type="String">3.5002**</Data></Cell><Cell ss:StyleID="s22"><Data ss:Type="String">3.9310***</Data></Cell></Row><Row><Cell ss:StyleID="s32"><Data ss:Type="String"></Data></Cell><Cell ss:StyleID="s22"><Data ss:Type="String">(2.47)</Data></Cell><Cell ss:StyleID="s22"><Data ss:Type="String">(3.04)</Data></Cell><Cell ss:StyleID="s22"><Data ss:Type="String">(2.47)</Data></Cell><Cell ss:StyleID="s22"><Data ss:Type="String">(3.04)</Data></Cell></Row><Row><Cell ss:StyleID="s32"><Data ss:Type="String">AF</Data></Cell><Cell ss:StyleID="s22"><Data ss:Type="String">-0.0060***</Data></Cell><Cell ss:StyleID="s22"><Data ss:Type="String">0.0003</Data></Cell><Cell ss:StyleID="s22"><Data ss:Type="String">-5.9964***</Data></Cell><Cell ss:StyleID="s22"><Data ss:Type="String">0.3012</Data></Cell></Row><Row><Cell ss:StyleID="s32"><Data ss:Type="String"></Data></Cell><Cell ss:StyleID="s22"><Data ss:Type="String">(-5.41)</Data></Cell><Cell ss:StyleID="s22"><Data ss:Type="String">(0.17)</Data></Cell><Cell ss:StyleID="s22"><Data ss:Type="String">(-5.41)</Data></Cell><Cell ss:StyleID="s22"><Data ss:Type="String">(0.17)</Data></Cell></Row><Row><Cell ss:StyleID="s32"><Data ss:Type="String">TONE</Data></Cell><Cell ss:StyleID="s22"><Data ss:Type="String"></Data></Cell><Cell ss:StyleID="s22"><Data ss:Type="String"></Data></Cell><Cell ss:StyleID="s22"><Data ss:Type="String">.</Data></Cell><Cell ss:StyleID="s22"><Data ss:Type="String">.</Data></Cell></Row><Row><Cell ss:StyleID="s32"><Data ss:Type="String"></Data></Cell><Cell ss:StyleID="s22"><Data ss:Type="String"></Data></Cell><Cell ss:StyleID="s22"><Data ss:Type="String"></Data></Cell><Cell ss:StyleID="s22"><Data ss:Type="String">(.)</Data></Cell><Cell ss:StyleID="s22"><Data ss:Type="String">(.)</Data></Cell></Row><Row><Cell ss:StyleID="s32"><Data ss:Type="String">Constant</Data></Cell><Cell ss:StyleID="s22"><Data ss:Type="String">-0.0044***</Data></Cell><Cell ss:StyleID="s22"><Data ss:Type="String">-0.0100***</Data></Cell><Cell ss:StyleID="s22"><Data ss:Type="String">-4.3539***</Data></Cell><Cell ss:StyleID="s22"><Data ss:Type="String">-10.0343***</Data></Cell></Row><Row><Cell ss:StyleID="s32"><Data ss:Type="String"></Data></Cell><Cell ss:StyleID="s22"><Data ss:Type="String">(-8.54)</Data></Cell><Cell ss:StyleID="s22"><Data ss:Type="String">(-2.73)</Data></Cell><Cell ss:StyleID="s22"><Data ss:Type="String">(-8.54)</Data></Cell><Cell ss:StyleID="s22"><Data ss:Type="String">(-2.73)</Data></Cell></Row><Row><Cell ss:StyleID="s32"><Data ss:Type="String"></Data></Cell><Cell ss:StyleID="s22"><Data ss:Type="String"></Data></Cell><Cell ss:StyleID="s22"><Data ss:Type="String"></Data></Cell><Cell ss:StyleID="s22"><Data ss:Type="String"></Data></Cell><Cell ss:StyleID="s22"><Data ss:Type="String"></Data></Cell></Row><Row><Cell ss:StyleID="s32"><Data ss:Type="String">Observations</Data></Cell><Cell ss:StyleID="s22"><Data ss:Type="String">17,556</Data></Cell><Cell ss:StyleID="s22"><Data ss:Type="String">17,556</Data></Cell><Cell ss:StyleID="s22"><Data ss:Type="String">17,556</Data></Cell><Cell ss:StyleID="s22"><Data ss:Type="String">17,556</Data></Cell></Row><Row><Cell ss:StyleID="s32"><Data ss:Type="String">Adjusted R-squared</Data></Cell><Cell ss:StyleID="s22"><Data ss:Type="String">0.0790</Data></Cell><Cell ss:StyleID="s22"><Data ss:Type="String">0.8457</Data></Cell><Cell ss:StyleID="s22"><Data ss:Type="String">0.0790</Data></Cell><Cell ss:StyleID="s22"><Data ss:Type="String">0.8457</Data></Cell></Row><Row><Cell ss:StyleID="s32"><Data ss:Type="String">Quarter FE</Data></Cell><Cell ss:StyleID="s22"><Data ss:Type="String">NO</Data></Cell><Cell ss:StyleID="s22"><Data ss:Type="String">YES</Data></Cell><Cell ss:StyleID="s22"><Data ss:Type="String">NO</Data></Cell><Cell ss:StyleID="s22"><Data ss:Type="String">YES</Data></Cell></Row><Row><Cell ss:StyleID="s32"><Data ss:Type="String">Firm FE</Data></Cell><Cell ss:StyleID="s22"><Data ss:Type="String">NO</Data></Cell><Cell ss:StyleID="s22"><Data ss:Type="String">YES</Data></Cell><Cell ss:StyleID="s22"><Data ss:Type="String">NO</Data></Cell><Cell ss:StyleID="s22"><Data ss:Type="String">YES</Data></Cell></Row><Row><Cell ss:StyleID="s33"><Data ss:Type="String">Industry-clustered SE</Data></Cell><Cell ss:StyleID="s23"><Data ss:Type="String">NO</Data></Cell><Cell ss:StyleID="s23"><Data ss:Type="String">YES</Data></Cell><Cell ss:StyleID="s23"><Data ss:Type="String">NO</Data></Cell><Cell ss:StyleID="s23"><Data ss:Type="String">YES</Data></Cell></Row><Row><Cell ss:StyleID="s24"><Data ss:Type="String">t-statistics in parentheses</Data></Cell></Row><Row><Cell ss:StyleID="s24"><Data ss:Type="String">*** p&lt;0.01, ** p&lt;0.05, * p&lt;0.1</Data></Cell></Row></Table><WorksheetOptions xmlns="urn:schemas-microsoft-com:office:excel"><ProtectedObjects>False</ProtectedObjects><ProtectedScenarios>False</ProtectedScenarios></WorksheetOptions></Worksheet></Workbook>